randomdice/__init__.py
randomdice/card.py
randomdice/coin.py
randomdice/die.py
randomdice/error.py
randomdice/spinwheel.py
randomdice/target.py
randomdice-0.2.1.dist-info/METADATA
randomdice-0.2.1.dist-info/WHEEL
randomdice-0.2.1.dist-info/top_level.txt
randomdice-0.2.1.dist-info/RECORD
