Metadata-Version: 2.4
Name: randomdice
Version: 0.2.1
Summary: A sample Python package
Home-page: https://github.com/aiwonderland/randomdice
Author: aiwonderland
Author-email: quantbit@126.com
Classifier: Programming Language :: Python :: 3
Classifier: License :: OSI Approved :: MIT License
Classifier: Operating System :: OS Independent
Requires-Python: >=3.8
Requires-Dist: requests>=2.25.0
